{
  "version": 2,
  "extractor": "pdffigures2",
  "figures": [
    {
      "url": "assets/figures/arxiv/2604.04660v1/fig-001.webp",
      "caption": "Figure 2: Cognitive cycle. Every input passes through safety gates before and after inference.",
      "page": 6,
      "index": 1,
      "width": 482,
      "height": 441
    },
    {
      "url": "assets/figures/arxiv/2604.04660v1/fig-002.webp",
      "caption": "Figure 4: Learning curve. P@4 improves with case base size; hard queries benefit most (+17.7%).",
      "page": 11,
      "index": 2,
      "width": 792,
      "height": 288
    },
    {
      "url": "assets/figures/arxiv/2604.04660v1/fig-003.webp",
      "caption": "Table 3: Retrieval performance (N = 800, 200 queries, K = 4). Non-overlapping CIs for hybrid vs dense cosine.",
      "page": 11,
      "index": 3,
      "width": 608,
      "height": 198
    },
    {
      "url": "assets/figures/arxiv/2604.04660v1/fig-004.webp",
      "caption": "Figure 3: Six-signal retrieval pipeline.",
      "page": 11,
      "index": 4,
      "width": 998,
      "height": 346
    },
    {
      "url": "assets/figures/arxiv/2604.04660v1/fig-005.webp",
      "caption": "Table 5: Operational scale over 23 days.",
      "page": 15,
      "index": 5,
      "width": 591,
      "height": 311
    },
    {
      "url": "assets/figures/arxiv/2604.04660v1/fig-006.webp",
      "caption": "Table 2: Specialist agents. Turn limits are defaults, configurable per profile.",
      "page": 7,
      "index": 6,
      "width": 992,
      "height": 216
    },
    {
      "url": "assets/figures/arxiv/2604.04660v1/fig-007.webp",
      "caption": "Table 7: D′ decision sheet—debug email (comms agent, tighter thresholds: modify 0.30, reject 0.50). 0.51 > 0.50 → REJECT.",
      "page": 18,
      "index": 7,
      "width": 675,
      "height": 263
    },
    {
      "url": "assets/figures/arxiv/2604.04660v1/fig-008.webp",
      "caption": "Table 6: D′ decision sheet—report delivery. 0.11 < 0.35 → ACCEPT.",
      "page": 17,
      "index": 8,
      "width": 604,
      "height": 313
    },
    {
      "url": "assets/figures/arxiv/2604.04660v1/fig-009.webp",
      "caption": "Table 10: Affect input signals gathered from CognitiveState.",
      "page": 32,
      "index": 9,
      "width": 812,
      "height": 277
    },
    {
      "url": "assets/figures/arxiv/2604.04660v1/fig-010.webp",
      "caption": "Figure 5: D′ scorer to normative calculus pipeline.",
      "page": 12,
      "index": 10,
      "width": 502,
      "height": 358
    },
    {
      "url": "assets/figures/arxiv/2604.04660v1/fig-011.webp",
      "caption": "Table 9: BEAM/Gleam properties and their use in Springdrift.",
      "page": 27,
      "index": 11,
      "width": 879,
      "height": 477
    },
    {
      "url": "assets/figures/arxiv/2604.04660v1/fig-012.webp",
      "caption": "Figure 6: OTP supervision tree. Red arrows show supervision relationships (parent restarts child on crash). Blue dashed arrows show typed message-passing channels. Each box is a BEAM process with its own heap and garbage collector.",
      "page": 27,
      "index": 12,
      "width": 741,
      "height": 377
    },
    {
      "url": "assets/figures/arxiv/2604.04660v1/fig-013.webp",
      "caption": "Figure 1: System architecture. The cognitive loop orchestrates all components via typed message-passing channels. This is a simplified diagram; the system can also create teams of cooperating subagents.",
      "page": 5,
      "index": 13,
      "width": 710,
      "height": 462
    },
    {
      "url": "assets/figures/arxiv/2604.04660v1/fig-014.webp",
      "caption": "Table 1: The ten memory stores.",
      "page": 5,
      "index": 14,
      "width": 687,
      "height": 302
    }
  ]
}